b4022/__init__.py
b4022-0.1.0.dist-info/WHEEL
b4022-0.1.0.dist-info/METADATA
b4022-0.1.0.dist-info/RECORD
