Metadata-Version: 2.1
Name: b4022
Version: 0.1.0
Summary: 
Author: Aisten
Author-email: gvilkson@gmail.com
Requires-Python: >=3.9,<4.0
Classifier: Programming Language :: Python :: 3
Classifier: Programming Language :: Python :: 3.10
Classifier: Programming Language :: Python :: 3.9
Requires-Dist: Django (>=4.0.5,<5.0.0)
Requires-Dist: requests (>=2.28.0,<3.0.0)
